scrubpy/__init__.py
scrubpy/_version.py
scrubpy/assistant.py
scrubpy/chat_assistant.py
scrubpy/cli.py
scrubpy/column_insights.py
scrubpy/core.py
scrubpy/eda_analysis.py
scrubpy/enhanced_cli.py
scrubpy/exceptions.py
scrubpy/export_profiling_report.py
scrubpy/llm_utils.py
scrubpy/preview.py
scrubpy/profiling.py
scrubpy/quality_analyzer.py
scrubpy/setup_wizard.py
scrubpy/smart_eda.py
scrubpy/utils.py
scrubpy/validation.py
scrubpy/config/__init__.py
scrubpy/config/settings.py
scrubpy/fonts/DejaVuSans.cw127.pkl
scrubpy/fonts/DejaVuSans.pkl
scrubpy/fonts/DejaVuSans.ttf
scrubpy/utils/__init__.py
scrubpy/utils/logging.py
scrubpy/utils/text_utils.py
scrubpy/web/__init__.py
scrubpy/web/launcher.py
scrubpy/web/modern_app.py
scrubpy-2.0.1.dist-info/licenses/LICENSE
scrubpy-2.0.1.dist-info/METADATA
scrubpy-2.0.1.dist-info/WHEEL
scrubpy-2.0.1.dist-info/entry_points.txt
scrubpy-2.0.1.dist-info/top_level.txt
scrubpy-2.0.1.dist-info/RECORD
