Metadata-Version: 2.4
Name: scrubpy
Version: 2.0.1
Summary: AI-powered data cleaning assistant with multiple interfaces
Home-page: https://github.com/Dhanushranga1/scrubpy
Author: Dhanush Ranga
Author-email: ScrubPy Team <support@scrubpy.dev>
Maintainer-email: ScrubPy Team <support@scrubpy.dev>
License: MIT
Project-URL: Homepage, https://github.com/Dhanushranga1/scrubpy
Project-URL: Documentation, https://scrubpy.readthedocs.io
Project-URL: Repository, https://github.com/Dhanushranga1/scrubpy.git
Project-URL: Bug Reports, https://github.com/Dhanushranga1/scrubpy/issues
Project-URL: Changelog, https://github.com/Dhanushranga1/scrubpy/blob/main/CHANGELOG.md
Keywords: data cleaning,data preprocessing,pandas,AI,machine learning,data science
Platform: any
Classifier: Development Status :: 4 - Beta
Classifier: Intended Audience :: Developers
Classifier: Intended Audience :: Science/Research
Classifier: Intended Audience :: End Users/Desktop
Classifier: License :: OSI Approved :: MIT License
Classifier: Operating System :: OS Independent
Classifier: Programming Language :: Python :: 3
Classifier: Programming Language :: Python :: 3.8
Classifier: Programming Language :: Python :: 3.9
Classifier: Programming Language :: Python :: 3.10
Classifier: Programming Language :: Python :: 3.11
Classifier: Programming Language :: Python :: 3.12
Classifier: Topic :: Scientific/Engineering :: Information Analysis
Classifier: Topic :: Software Development :: Libraries :: Python Modules
Classifier: Topic :: Utilities
Requires-Python: >=3.8
License-File: LICENSE
Requires-Dist: pandas>=1.3.0
Requires-Dist: numpy>=1.21.0
Requires-Dist: scipy>=1.7.0
Requires-Dist: typer>=0.9.0
Requires-Dist: rich>=13.0.0
Requires-Dist: InquirerPy>=0.3.0
Requires-Dist: PyYAML>=6.0.0
Requires-Dist: pydantic>=1.10.0
Requires-Dist: matplotlib>=3.5.0
Requires-Dist: seaborn>=0.11.0
Requires-Dist: plotly>=5.0.0
Requires-Dist: fpdf2>=2.5.0
Requires-Dist: streamlit>=1.25.0
Requires-Dist: streamlit-aggrid>=0.3.0
Requires-Dist: scikit-learn>=1.0.0
Requires-Dist: phonenumbers>=8.13.0
Requires-Dist: openpyxl>=3.0.0
Requires-Dist: xlrd>=2.0.0
Requires-Dist: pyarrow>=10.0.0
Requires-Dist: requests>=2.28.0
Requires-Dist: python-dateutil>=2.8.0
Provides-Extra: ai
Requires-Dist: ollama>=0.1.0; extra == "ai"
Requires-Dist: openai>=1.0.0; extra == "ai"
Requires-Dist: anthropic>=0.3.0; extra == "ai"
Requires-Dist: InquirerPy>=0.3.4; extra == "ai"
Requires-Dist: psutil>=5.8.0; extra == "ai"
Provides-Extra: dev
Requires-Dist: pytest>=6.0; extra == "dev"
Requires-Dist: pytest-cov>=2.0; extra == "dev"
Requires-Dist: black>=22.0; extra == "dev"
Requires-Dist: flake8>=4.0; extra == "dev"
Requires-Dist: mypy>=0.950; extra == "dev"
Requires-Dist: pre-commit>=2.15.0; extra == "dev"
Provides-Extra: performance
Requires-Dist: polars>=0.18.0; extra == "performance"
Requires-Dist: fastparquet>=0.8.0; extra == "performance"
Provides-Extra: all
Requires-Dist: ollama>=0.1.0; extra == "all"
Requires-Dist: openai>=1.0.0; extra == "all"
Requires-Dist: anthropic>=0.3.0; extra == "all"
Requires-Dist: pytest>=6.0; extra == "all"
Requires-Dist: pytest-cov>=2.0; extra == "all"
Requires-Dist: black>=22.0; extra == "all"
Requires-Dist: flake8>=4.0; extra == "all"
Requires-Dist: mypy>=0.950; extra == "all"
Requires-Dist: polars>=0.18.0; extra == "all"
Requires-Dist: fastparquet>=0.8.0; extra == "all"
Dynamic: author
Dynamic: home-page
Dynamic: license-file
Dynamic: platform
Dynamic: requires-python
